[
  {
    "id": "1c6704e4-4b68-40ae-b64a-567b365c4746",
    "url": "https://www.youtube.com/watch?v=mz9fYOAAyNc&list=RDmz9fYOAAyNc",
    "title": "Morning Mix by JIRA | Soul Groove and 00s Vibes",
    "description": null,
    "image_url": "https://i.ytimg.com/vi/mz9fYOAAyNc/maxresdefault.jpg",
    "memo": null,
    "category": "라이프",
    "tags": [],
    "source_type": "other",
    "is_favorite": false,
    "created_at": "2026-04-23T04:11:04.352Z"
  },
  {
    "id": "689e009d-94bc-4089-89ef-ab6f4a5d23fd",
    "url": "/uploads/insights/9541127d-20a8-4078-b740-31e052ed4f89.JPG",
    "title": "스크린샷 2026-04-15 오후 6.09.52",
    "description": null,
    "image_url": "/uploads/insights/9541127d-20a8-4078-b740-31e052ed4f89.JPG",
    "memo": null,
    "category": "크리에이티브",
    "tags": [
      "이미지",
      "레퍼런스"
    ],
    "source_type": "image",
    "is_favorite": false,
    "created_at": "2026-04-23T05:22:52.375Z"
  },
  {
    "id": "69f1bc81-4b20-42de-83e2-7ca26ed46934",
    "url": "/uploads/insights/44ed1635-f7db-4fea-b6cc-430847a7cafc.JPG",
    "title": "스크린샷 2026-04-15 오후 6.10.05",
    "description": null,
    "image_url": "/uploads/insights/44ed1635-f7db-4fea-b6cc-430847a7cafc.JPG",
    "memo": null,
    "category": "크리에이티브",
    "tags": [
      "이미지",
      "레퍼런스"
    ],
    "source_type": "image",
    "is_favorite": false,
    "created_at": "2026-04-23T05:22:52.393Z"
  },
  {
    "id": "a38357a5-849e-4a9b-95db-ae169ac71c59",
    "url": "/uploads/insights/32dec711-02f8-44f9-a22a-f3cf43ecbef0.JPG",
    "title": "스크린샷 2026-04-15 오후 6.10.18",
    "description": null,
    "image_url": "/uploads/insights/32dec711-02f8-44f9-a22a-f3cf43ecbef0.JPG",
    "memo": null,
    "category": "크리에이티브",
    "tags": [
      "이미지",
      "레퍼런스"
    ],
    "source_type": "image",
    "is_favorite": false,
    "created_at": "2026-04-23T05:22:52.403Z"
  },
  {
    "id": "48f4ff09-cdcf-48f1-8ea0-ba3efdb6324d",
    "url": "/uploads/insights/ad801d66-f194-4510-a718-6ea578396818.JPG",
    "title": "스크린샷 2026-04-15 오후 10.51.35",
    "description": null,
    "image_url": "/uploads/insights/ad801d66-f194-4510-a718-6ea578396818.JPG",
    "memo": null,
    "category": "크리에이티브",
    "tags": [
      "이미지",
      "레퍼런스"
    ],
    "source_type": "image",
    "is_favorite": false,
    "created_at": "2026-04-23T05:22:52.441Z"
  },
  {
    "id": "ae9f594b-15d0-42ae-8365-a0211700dbb1",
    "url": "/uploads/insights/214ba9cf-0d0e-499b-8411-98beaf0a67f6.JPG",
    "title": "스크린샷 2026-04-15 오후 10.51.46",
    "description": null,
    "image_url": "/uploads/insights/214ba9cf-0d0e-499b-8411-98beaf0a67f6.JPG",
    "memo": null,
    "category": "크리에이티브",
    "tags": [
      "이미지",
      "레퍼런스"
    ],
    "source_type": "image",
    "is_favorite": false,
    "created_at": "2026-04-23T05:22:52.453Z"
  },
  {
    "id": "55298a01-0bd9-4121-beac-188fe1924303",
    "url": "/uploads/insights/6611f724-6637-48e7-b3c5-acebfb3448e7.JPG",
    "title": "스크린샷 2026-04-15 오후 10.52.00",
    "description": null,
    "image_url": "/uploads/insights/6611f724-6637-48e7-b3c5-acebfb3448e7.JPG",
    "memo": null,
    "category": "크리에이티브",
    "tags": [
      "이미지",
      "레퍼런스"
    ],
    "source_type": "image",
    "is_favorite": false,
    "created_at": "2026-04-23T05:22:52.464Z"
  },
  {
    "id": "ca9a108f-5548-4555-830e-aebb460b60d6",
    "url": "/uploads/insights/623b0a1a-6bae-4bd8-a4e2-51eccfd2e9fb.JPG",
    "title": "스크린샷 2026-04-15 오후 10.52.12",
    "description": null,
    "image_url": "/uploads/insights/623b0a1a-6bae-4bd8-a4e2-51eccfd2e9fb.JPG",
    "memo": null,
    "category": "크리에이티브",
    "tags": [
      "이미지",
      "레퍼런스"
    ],
    "source_type": "image",
    "is_favorite": false,
    "created_at": "2026-04-23T05:22:52.474Z"
  },
  {
    "id": "8f2b52d8-3130-4a5c-bce6-82cc5f2227e9",
    "url": "/uploads/insights/8256a6da-d737-4ff5-8ef8-c0ace5f7c3a7.JPG",
    "title": "스크린샷 2026-04-15 오후 10.52.18",
    "description": null,
    "image_url": "/uploads/insights/8256a6da-d737-4ff5-8ef8-c0ace5f7c3a7.JPG",
    "memo": null,
    "category": "크리에이티브",
    "tags": [
      "이미지",
      "레퍼런스"
    ],
    "source_type": "image",
    "is_favorite": false,
    "created_at": "2026-04-23T05:22:52.497Z"
  },
  {
    "id": "08c6dd44-62c4-4dd0-96e4-afc0daebb716",
    "url": "/uploads/insights/361e3a05-567c-4fb3-b21a-336df23c934e.JPG",
    "title": "스크린샷 2026-04-15 오후 10.52.22",
    "description": null,
    "image_url": "/uploads/insights/361e3a05-567c-4fb3-b21a-336df23c934e.JPG",
    "memo": null,
    "category": "크리에이티브",
    "tags": [
      "이미지",
      "레퍼런스"
    ],
    "source_type": "image",
    "is_favorite": false,
    "created_at": "2026-04-23T05:22:52.506Z"
  },
  {
    "id": "8a5264af-fb77-4f73-9f52-36948ac87d59",
    "url": "/uploads/insights/e0368828-6d63-437f-97a6-1883e7f7f229.JPG",
    "title": "스크린샷 2026-04-15 오후 10.52.25",
    "description": null,
    "image_url": "/uploads/insights/e0368828-6d63-437f-97a6-1883e7f7f229.JPG",
    "memo": null,
    "category": "크리에이티브",
    "tags": [
      "이미지",
      "레퍼런스"
    ],
    "source_type": "image",
    "is_favorite": false,
    "created_at": "2026-04-23T05:22:52.513Z"
  },
  {
    "id": "8d18a4a0-e017-46b0-8a60-658672e8e98a",
    "url": "https://www.youtube.com/watch?v=c-a4GBOxhXQ&t=698s",
    "title": "나의 AI 에이전트 전환기 (w. 클로드 코드, 오픈클로)",
    "description": null,
    "image_url": "https://i.ytimg.com/vi/c-a4GBOxhXQ/maxresdefault.jpg",
    "memo": null,
    "category": "비즈니스",
    "tags": [],
    "source_type": "video",
    "is_favorite": false,
    "created_at": "2026-04-23T05:34:07.543Z"
  }
]